nexus/__init__.py
nexus/apps.py
nexus/checks.py
nexus/compat.py
nexus/conf.py
nexus/modules.py
nexus/sites.py
nexus/media/css/facebox.css
nexus/media/css/nexus.css
nexus/media/img/favicon.png
nexus/media/img/loading.gif
nexus/media/img/nexus_logo.png
nexus/media/img/admin/icon_add.gif
nexus/media/img/admin/icon_change.gif
nexus/media/img/admin/icon_delete.gif
nexus/media/img/admin/nav-bg.gif
nexus/media/img/facebox/closelabel.png
nexus/media/img/facebox/loading.gif
nexus/media/js/nexus.js
nexus/media/js/lib/jquery.js
nexus/media/js/lib/facebox/facebox.js
nexus/templates/nexus/base.html
nexus/templates/nexus/dashboard.html
nexus/templates/nexus/module.html
nexus/templates/nexus/navigation.html
nexus/templatetags/__init__.py
nexus/templatetags/nexus_helpers.py
nexus_yplan-2.1.2.dist-info/LICENSE
nexus_yplan-2.1.2.dist-info/METADATA
nexus_yplan-2.1.2.dist-info/WHEEL
nexus_yplan-2.1.2.dist-info/top_level.txt
nexus_yplan-2.1.2.dist-info/RECORD
