Metadata-Version: 2.1
Name: nexus-yplan
Version: 2.1.2
Summary: Nexus is a pluggable admin application in Django. It's designed to give you a simple design and architecture for building admin applications.
Home-page: https://github.com/adamchainz/nexus
Author: Disqus
Author-email: opensource@disqus.com
Maintainer: Adam Johnson
Maintainer-email: me@adamj.eu
License: Apache License 2.0
Platform: UNKNOWN
Classifier: Development Status :: 7 - Inactive
Classifier: Framework :: Django
Classifier: Framework :: Django :: 1.11
Classifier: Framework :: Django :: 2.0
Classifier: Framework :: Django :: 2.1
Classifier: Framework :: Django :: 2.2
Classifier: Intended Audience :: Developers
Classifier: Intended Audience :: System Administrators
Classifier: License :: OSI Approved :: Apache Software License
Classifier: Natural Language :: English
Classifier: Operating System :: OS Independent
Classifier: Programming Language :: Python :: 3 :: Only
Classifier: Programming Language :: Python :: 3
Classifier: Programming Language :: Python :: 3.4
Classifier: Programming Language :: Python :: 3.5
Classifier: Programming Language :: Python :: 3.6
Classifier: Topic :: Software Development
Requires-Python: >=3.4
Requires-Dist: Django (>=1.11)
